{
    "letztes_spiel": {
        "spiel": "Jordanien vs. Algerien",
        "ergebnis": "1:2"
    },
    "spektakel": {
        "spiel": "England vs. Kroatien",
        "ergebnis": "4:2",
        "experten": "Johann Straub"
    },
    "differenz": {
        "spiel": "Kanada vs. Katar",
        "tipp": "0:1 (Ergebnis 6:0)",
        "tipper": "Hargun Weitz"
    },
    "solo_experte": {
        "spiel": "Schottland vs. Marokko",
        "tipp": "0:1",
        "experten": "Adriana Zekaj"
    },
    "meist_richtig": "Mexiko vs. Südafrika (8x exakt)",
    "wenigst_richtig": "Australien vs. Türkei (30x komplett falsch)",
    "gesamt_tabelle": [
        {
            "name": "Eduardo Barbosa",
            "punkte": 77,
            "exakt": 8,
            "differenz": 5,
            "tendenz": 15,
            "platz": 1
        },
        {
            "name": "Jonas Drtil",
            "punkte": 75,
            "exakt": 8,
            "differenz": 5,
            "tendenz": 14,
            "platz": 2
        },
        {
            "name": "Noah Langmaack",
            "punkte": 72,
            "exakt": 5,
            "differenz": 6,
            "tendenz": 17,
            "platz": 3
        },
        {
            "name": "Sven Weiland",
            "punkte": 70,
            "exakt": 9,
            "differenz": 2,
            "tendenz": 14,
            "platz": 4
        },
        {
            "name": "Jaden Göhre",
            "punkte": 70,
            "exakt": 7,
            "differenz": 4,
            "tendenz": 15,
            "platz": 5
        },
        {
            "name": "Eiko Sender",
            "punkte": 69,
            "exakt": 5,
            "differenz": 5,
            "tendenz": 17,
            "platz": 6
        },
        {
            "name": "Johann Straub",
            "punkte": 68,
            "exakt": 6,
            "differenz": 4,
            "tendenz": 16,
            "platz": 7
        },
        {
            "name": "Sophia Hermann",
            "punkte": 64,
            "exakt": 3,
            "differenz": 4,
            "tendenz": 20,
            "platz": 8
        },
        {
            "name": "Clemens Kukula",
            "punkte": 62,
            "exakt": 2,
            "differenz": 8,
            "tendenz": 15,
            "platz": 9
        },
        {
            "name": "Tim Bredlau",
            "punkte": 61,
            "exakt": 4,
            "differenz": 3,
            "tendenz": 18,
            "platz": 10
        },
        {
            "name": "Koder Farij",
            "punkte": 61,
            "exakt": 4,
            "differenz": 3,
            "tendenz": 18,
            "platz": 10
        },
        {
            "name": "Tim König",
            "punkte": 61,
            "exakt": 4,
            "differenz": 3,
            "tendenz": 18,
            "platz": 10
        },
        {
            "name": "Mika Lorenz",
            "punkte": 59,
            "exakt": 5,
            "differenz": 3,
            "tendenz": 15,
            "platz": 13
        },
        {
            "name": "Lea Sauer",
            "punkte": 59,
            "exakt": 4,
            "differenz": 5,
            "tendenz": 14,
            "platz": 14
        },
        {
            "name": "Billie Resch",
            "punkte": 59,
            "exakt": 4,
            "differenz": 3,
            "tendenz": 17,
            "platz": 15
        },
        {
            "name": "Maxim Isaac",
            "punkte": 58,
            "exakt": 3,
            "differenz": 6,
            "tendenz": 14,
            "platz": 16
        },
        {
            "name": "Roy Chi",
            "punkte": 57,
            "exakt": 4,
            "differenz": 3,
            "tendenz": 16,
            "platz": 17
        },
        {
            "name": "Adriana Zekaj",
            "punkte": 57,
            "exakt": 3,
            "differenz": 3,
            "tendenz": 18,
            "platz": 18
        },
        {
            "name": "Alex Schindler",
            "punkte": 57,
            "exakt": 2,
            "differenz": 5,
            "tendenz": 17,
            "platz": 19
        },
        {
            "name": "Luis Pfeiffer",
            "punkte": 56,
            "exakt": 3,
            "differenz": 2,
            "tendenz": 19,
            "platz": 20
        },
        {
            "name": "Deborah Berker",
            "punkte": 54,
            "exakt": 1,
            "differenz": 4,
            "tendenz": 19,
            "platz": 21
        },
        {
            "name": "Fynn Lotz",
            "punkte": 53,
            "exakt": 6,
            "differenz": 3,
            "tendenz": 10,
            "platz": 22
        },
        {
            "name": "Gabriela Susur",
            "punkte": 53,
            "exakt": 1,
            "differenz": 5,
            "tendenz": 17,
            "platz": 23
        },
        {
            "name": "Sophia Varga",
            "punkte": 52,
            "exakt": 3,
            "differenz": 2,
            "tendenz": 17,
            "platz": 24
        },
        {
            "name": "Emilie Maurice",
            "punkte": 50,
            "exakt": 4,
            "differenz": 4,
            "tendenz": 11,
            "platz": 25
        },
        {
            "name": "Connor Lüning",
            "punkte": 48,
            "exakt": 1,
            "differenz": 2,
            "tendenz": 19,
            "platz": 26
        },
        {
            "name": "Johanna Stroman",
            "punkte": 47,
            "exakt": 3,
            "differenz": 3,
            "tendenz": 13,
            "platz": 27
        },
        {
            "name": "Max Zapletal",
            "punkte": 46,
            "exakt": 0,
            "differenz": 4,
            "tendenz": 17,
            "platz": 28
        },
        {
            "name": "Hargun Weitz",
            "punkte": 44,
            "exakt": 3,
            "differenz": 2,
            "tendenz": 13,
            "platz": 29
        },
        {
            "name": "Caylin Daubner",
            "punkte": 44,
            "exakt": 1,
            "differenz": 0,
            "tendenz": 20,
            "platz": 30
        }
    ],
    "form_tabelle_letzte_7": [
        {
            "name": "Eiko Sender",
            "punkte": 17,
            "platz": 1
        },
        {
            "name": "Jaden Göhre",
            "punkte": 15,
            "platz": 2
        },
        {
            "name": "Eduardo Barbosa",
            "punkte": 14,
            "platz": 3
        },
        {
            "name": "Tim König",
            "punkte": 14,
            "platz": 4
        },
        {
            "name": "Mika Lorenz",
            "punkte": 14,
            "platz": 5
        },
        {
            "name": "Luis Pfeiffer",
            "punkte": 14,
            "platz": 6
        },
        {
            "name": "Johann Straub",
            "punkte": 13,
            "platz": 7
        },
        {
            "name": "Koder Farij",
            "punkte": 13,
            "platz": 8
        },
        {
            "name": "Lea Sauer",
            "punkte": 13,
            "platz": 9
        },
        {
            "name": "Billie Resch",
            "punkte": 13,
            "platz": 10
        },
        {
            "name": "Fynn Lotz",
            "punkte": 13,
            "platz": 11
        },
        {
            "name": "Max Zapletal",
            "punkte": 13,
            "platz": 12
        },
        {
            "name": "Noah Langmaack",
            "punkte": 12,
            "platz": 13
        },
        {
            "name": "Sven Weiland",
            "punkte": 12,
            "platz": 14
        },
        {
            "name": "Alex Schindler",
            "punkte": 12,
            "platz": 15
        },
        {
            "name": "Jonas Drtil",
            "punkte": 11,
            "platz": 16
        },
        {
            "name": "Sophia Hermann",
            "punkte": 11,
            "platz": 17
        },
        {
            "name": "Emilie Maurice",
            "punkte": 11,
            "platz": 18
        },
        {
            "name": "Tim Bredlau",
            "punkte": 10,
            "platz": 19
        },
        {
            "name": "Roy Chi",
            "punkte": 10,
            "platz": 20
        },
        {
            "name": "Hargun Weitz",
            "punkte": 9,
            "platz": 21
        },
        {
            "name": "Clemens Kukula",
            "punkte": 8,
            "platz": 22
        },
        {
            "name": "Maxim Isaac",
            "punkte": 8,
            "platz": 23
        },
        {
            "name": "Deborah Berker",
            "punkte": 8,
            "platz": 24
        },
        {
            "name": "Sophia Varga",
            "punkte": 8,
            "platz": 25
        },
        {
            "name": "Adriana Zekaj",
            "punkte": 7,
            "platz": 26
        },
        {
            "name": "Gabriela Susur",
            "punkte": 7,
            "platz": 27
        },
        {
            "name": "Connor Lüning",
            "punkte": 7,
            "platz": 28
        },
        {
            "name": "Johanna Stroman",
            "punkte": 7,
            "platz": 29
        },
        {
            "name": "Caylin Daubner",
            "punkte": 2,
            "platz": 30
        }
    ],
    "alle_spiele_stats": [
        {
            "spiel": "Mexiko vs. Südafrika",
            "phase": "Gruppe",
            "beendet": true,
            "ergebnis": "2:0",
            "haeufigster_tipp": "2:1",
            "anzahl_4": 8,
            "anzahl_3": 4,
            "anzahl_2": 18
        },
        {
            "spiel": "Südkorea vs. Tschechien",
            "phase": "Gruppe",
            "beendet": true,
            "ergebnis": "2:1",
            "haeufigster_tipp": "1:1",
            "anzahl_4": 6,
            "anzahl_3": 2,
            "anzahl_2": 0
        },
        {
            "spiel": "Kanada vs. Bosnien",
            "phase": "Gruppe",
            "beendet": true,
            "ergebnis": "1:1",
            "haeufigster_tipp": "2:0",
            "anzahl_4": 4,
            "anzahl_3": 0,
            "anzahl_2": 1
        },
        {
            "spiel": "USA vs. Paraguay",
            "phase": "Gruppe",
            "beendet": true,
            "ergebnis": "4:1",
            "haeufigster_tipp": "2:1",
            "anzahl_4": 0,
            "anzahl_3": 0,
            "anzahl_2": 23
        },
        {
            "spiel": "Haiti vs. Schottland",
            "phase": "Gruppe",
            "beendet": true,
            "ergebnis": "0:1",
            "haeufigster_tipp": "0:2",
            "anzahl_4": 6,
            "anzahl_3": 2,
            "anzahl_2": 19
        },
        {
            "spiel": "Australien vs. Türkei",
            "phase": "Gruppe",
            "beendet": true,
            "ergebnis": "2:0",
            "haeufigster_tipp": "1:2",
            "anzahl_4": 0,
            "anzahl_3": 0,
            "anzahl_2": 0
        },
        {
            "spiel": "Brasilien vs. Marokko",
            "phase": "Gruppe",
            "beendet": true,
            "ergebnis": "1:1",
            "haeufigster_tipp": "2:1",
            "anzahl_4": 0,
            "anzahl_3": 0,
            "anzahl_2": 4
        },
        {
            "spiel": "Katar vs. Schweiz",
            "phase": "Gruppe",
            "beendet": true,
            "ergebnis": "1:1",
            "haeufigster_tipp": "0:2",
            "anzahl_4": 2,
            "anzahl_3": 0,
            "anzahl_2": 0
        },
        {
            "spiel": "Elfenbeinküste vs. Ecuador",
            "phase": "Gruppe",
            "beendet": true,
            "ergebnis": "1:0",
            "haeufigster_tipp": "1:2",
            "anzahl_4": 2,
            "anzahl_3": 2,
            "anzahl_2": 2
        },
        {
            "spiel": "DEUTSCHLAND vs. Curacao",
            "phase": "Gruppe",
            "beendet": true,
            "ergebnis": "7:1",
            "haeufigster_tipp": "4:0",
            "anzahl_4": 0,
            "anzahl_3": 1,
            "anzahl_2": 29
        },
        {
            "spiel": "Niederlande vs. Japan",
            "phase": "Gruppe",
            "beendet": true,
            "ergebnis": "2:2",
            "haeufigster_tipp": "2:1",
            "anzahl_4": 3,
            "anzahl_3": 0,
            "anzahl_2": 2
        },
        {
            "spiel": "Schweden vs. Tunesien",
            "phase": "Gruppe",
            "beendet": true,
            "ergebnis": "5:1",
            "haeufigster_tipp": "2:0",
            "anzahl_4": 0,
            "anzahl_3": 0,
            "anzahl_2": 23
        },
        {
            "spiel": "Spanien vs. Kap Verde",
            "phase": "Gruppe",
            "beendet": true,
            "ergebnis": "0:0",
            "haeufigster_tipp": "3:0",
            "anzahl_4": 0,
            "anzahl_3": 0,
            "anzahl_2": 0
        },
        {
            "spiel": "Saudi-Arabien vs. Uruguay",
            "phase": "Gruppe",
            "beendet": true,
            "ergebnis": "1:1",
            "haeufigster_tipp": "0:2",
            "anzahl_4": 1,
            "anzahl_3": 0,
            "anzahl_2": 1
        },
        {
            "spiel": "Belgien vs. Ägypten",
            "phase": "Gruppe",
            "beendet": true,
            "ergebnis": "1:1",
            "haeufigster_tipp": "2:1",
            "anzahl_4": 0,
            "anzahl_3": 0,
            "anzahl_2": 2
        },
        {
            "spiel": "Iran vs. Neuseeland",
            "phase": "Gruppe",
            "beendet": true,
            "ergebnis": "2:2",
            "haeufigster_tipp": "1:0",
            "anzahl_4": 1,
            "anzahl_3": 0,
            "anzahl_2": 5
        },
        {
            "spiel": "Frankreich vs. Senegal",
            "phase": "Gruppe",
            "beendet": true,
            "ergebnis": "3:1",
            "haeufigster_tipp": "3:1",
            "anzahl_4": 11,
            "anzahl_3": 2,
            "anzahl_2": 17
        },
        {
            "spiel": "Irak vs. Norwegen",
            "phase": "Gruppe",
            "beendet": true,
            "ergebnis": "1:4",
            "haeufigster_tipp": "0:2",
            "anzahl_4": 1,
            "anzahl_3": 2,
            "anzahl_2": 25
        },
        {
            "spiel": "Argentinien vs. Algerien",
            "phase": "Gruppe",
            "beendet": true,
            "ergebnis": "3:0",
            "haeufigster_tipp": "3:1",
            "anzahl_4": 7,
            "anzahl_3": 1,
            "anzahl_2": 22
        },
        {
            "spiel": "Österreich vs. Jordanien",
            "phase": "Gruppe",
            "beendet": true,
            "ergebnis": "3:1",
            "haeufigster_tipp": "2:0",
            "anzahl_4": 2,
            "anzahl_3": 18,
            "anzahl_2": 8
        },
        {
            "spiel": "England vs. Kroatien",
            "phase": "Gruppe",
            "beendet": true,
            "ergebnis": "4:2",
            "haeufigster_tipp": "2:1",
            "anzahl_4": 1,
            "anzahl_3": 2,
            "anzahl_2": 16
        },
        {
            "spiel": "Portugal vs. DRK",
            "phase": "Gruppe",
            "beendet": true,
            "ergebnis": "1:1",
            "haeufigster_tipp": "3:0",
            "anzahl_4": 0,
            "anzahl_3": 0,
            "anzahl_2": 0
        },
        {
            "spiel": "Ghana vs. Panama",
            "phase": "Gruppe",
            "beendet": true,
            "ergebnis": "1:0",
            "haeufigster_tipp": "2:1",
            "anzahl_4": 6,
            "anzahl_3": 9,
            "anzahl_2": 7
        },
        {
            "spiel": "Usbekistan vs. Kolumbien",
            "phase": "Gruppe",
            "beendet": true,
            "ergebnis": "1:3",
            "haeufigster_tipp": "0:2",
            "anzahl_4": 3,
            "anzahl_3": 14,
            "anzahl_2": 11
        },
        {
            "spiel": "Tschechien vs. Südafrika",
            "phase": "Gruppe",
            "beendet": true,
            "ergebnis": "1:1",
            "haeufigster_tipp": "2:0",
            "anzahl_4": 2,
            "anzahl_3": 0,
            "anzahl_2": 1
        },
        {
            "spiel": "Schweiz vs. Bosnien",
            "phase": "Gruppe",
            "beendet": true,
            "ergebnis": "4:1",
            "haeufigster_tipp": "2:1",
            "anzahl_4": 0,
            "anzahl_3": 0,
            "anzahl_2": 14
        },
        {
            "spiel": "Kanada vs. Katar",
            "phase": "Gruppe",
            "beendet": true,
            "ergebnis": "6:0",
            "haeufigster_tipp": "2:1",
            "anzahl_4": 0,
            "anzahl_3": 0,
            "anzahl_2": 28
        },
        {
            "spiel": "Mexiko vs. Südkorea",
            "phase": "Gruppe",
            "beendet": true,
            "ergebnis": "1:0",
            "haeufigster_tipp": "2:1",
            "anzahl_4": 0,
            "anzahl_3": 7,
            "anzahl_2": 6
        },
        {
            "spiel": "USA vs. Australien",
            "phase": "Gruppe",
            "beendet": true,
            "ergebnis": "2:0",
            "haeufigster_tipp": "2:1",
            "anzahl_4": 3,
            "anzahl_3": 4,
            "anzahl_2": 18
        },
        {
            "spiel": "Schottland vs. Marokko",
            "phase": "Gruppe",
            "beendet": true,
            "ergebnis": "0:1",
            "haeufigster_tipp": "0:2",
            "anzahl_4": 1,
            "anzahl_3": 5,
            "anzahl_2": 12
        },
        {
            "spiel": "Brasilien vs. Haiti",
            "phase": "Gruppe",
            "beendet": true,
            "ergebnis": "3:0",
            "haeufigster_tipp": "3:0",
            "anzahl_4": 11,
            "anzahl_3": 1,
            "anzahl_2": 17
        },
        {
            "spiel": "Türkei vs. Paraguay",
            "phase": "Gruppe",
            "beendet": true,
            "ergebnis": "0:1",
            "haeufigster_tipp": "2:0",
            "anzahl_4": 0,
            "anzahl_3": 0,
            "anzahl_2": 0
        },
        {
            "spiel": "Niederlande vs. Schweden",
            "phase": "Gruppe",
            "beendet": true,
            "ergebnis": "5:1",
            "haeufigster_tipp": "2:1",
            "anzahl_4": 0,
            "anzahl_3": 0,
            "anzahl_2": 19
        },
        {
            "spiel": "DEUTSCHLAND vs. Elfenbeinküste",
            "phase": "Gruppe",
            "beendet": true,
            "ergebnis": "2:1",
            "haeufigster_tipp": "3:1",
            "anzahl_4": 6,
            "anzahl_3": 1,
            "anzahl_2": 23
        },
        {
            "spiel": "Ecuador vs. Curacao",
            "phase": "Gruppe",
            "beendet": true,
            "ergebnis": "0:0",
            "haeufigster_tipp": "3:1",
            "anzahl_4": 0,
            "anzahl_3": 0,
            "anzahl_2": 1
        },
        {
            "spiel": "Tunesien vs. Japan",
            "phase": "Gruppe",
            "beendet": true,
            "ergebnis": "0:4",
            "haeufigster_tipp": "1:2",
            "anzahl_4": 0,
            "anzahl_3": 0,
            "anzahl_2": 24
        },
        {
            "spiel": "Spanien vs. Saudi-Arabien",
            "phase": "Gruppe",
            "beendet": true,
            "ergebnis": "4:0",
            "haeufigster_tipp": "3:0",
            "anzahl_4": 2,
            "anzahl_3": 0,
            "anzahl_2": 27
        },
        {
            "spiel": "Belgien vs. Iran",
            "phase": "Gruppe",
            "beendet": true,
            "ergebnis": "0:0",
            "haeufigster_tipp": "2:1",
            "anzahl_4": 0,
            "anzahl_3": 0,
            "anzahl_2": 2
        },
        {
            "spiel": "Uruguay vs. Kap Verde",
            "phase": "Gruppe",
            "beendet": true,
            "ergebnis": "2:2",
            "haeufigster_tipp": "2:0",
            "anzahl_4": 0,
            "anzahl_3": 0,
            "anzahl_2": 5
        },
        {
            "spiel": "Neuseeland vs. Ägypten",
            "phase": "Gruppe",
            "beendet": true,
            "ergebnis": "1:3",
            "haeufigster_tipp": "1:2",
            "anzahl_4": 0,
            "anzahl_3": 7,
            "anzahl_2": 11
        },
        {
            "spiel": "Argentinien vs. Österreich",
            "phase": "Gruppe",
            "beendet": true,
            "ergebnis": "2:0",
            "haeufigster_tipp": "3:1",
            "anzahl_4": 2,
            "anzahl_3": 10,
            "anzahl_2": 14
        },
        {
            "spiel": "Frankreich vs. Irak",
            "phase": "Gruppe",
            "beendet": true,
            "ergebnis": "3:0",
            "haeufigster_tipp": "3:0",
            "anzahl_4": 15,
            "anzahl_3": 4,
            "anzahl_2": 10
        },
        {
            "spiel": "Norwegen vs. Senegal",
            "phase": "Gruppe",
            "beendet": true,
            "ergebnis": "3:2",
            "haeufigster_tipp": "2:1",
            "anzahl_4": 3,
            "anzahl_3": 6,
            "anzahl_2": 9
        },
        {
            "spiel": "Jordanien vs. Algerien",
            "phase": "Gruppe",
            "beendet": true,
            "ergebnis": "1:2",
            "haeufigster_tipp": "1:2",
            "anzahl_4": 7,
            "anzahl_3": 7,
            "anzahl_2": 7
        },
        {
            "spiel": "Portugal vs. Usbekistan",
            "phase": "Gruppe",
            "beendet": false,
            "ergebnis": "-:-",
            "haeufigster_tipp": "-:-",
            "anzahl_4": 0,
            "anzahl_3": 0,
            "anzahl_2": 0
        },
        {
            "spiel": "England vs. Ghana",
            "phase": "Gruppe",
            "beendet": false,
            "ergebnis": "-:-",
            "haeufigster_tipp": "-:-",
            "anzahl_4": 0,
            "anzahl_3": 0,
            "anzahl_2": 0
        },
        {
            "spiel": "Panama vs. Kroatien",
            "phase": "Gruppe",
            "beendet": false,
            "ergebnis": "-:-",
            "haeufigster_tipp": "-:-",
            "anzahl_4": 0,
            "anzahl_3": 0,
            "anzahl_2": 0
        },
        {
            "spiel": "Kolumbien vs. DRK",
            "phase": "Gruppe",
            "beendet": false,
            "ergebnis": "-:-",
            "haeufigster_tipp": "-:-",
            "anzahl_4": 0,
            "anzahl_3": 0,
            "anzahl_2": 0
        },
        {
            "spiel": "Schweiz vs. Kanada",
            "phase": "Gruppe",
            "beendet": false,
            "ergebnis": "-:-",
            "haeufigster_tipp": "-:-",
            "anzahl_4": 0,
            "anzahl_3": 0,
            "anzahl_2": 0
        },
        {
            "spiel": "Bosnien vs. Katar",
            "phase": "Gruppe",
            "beendet": false,
            "ergebnis": "-:-",
            "haeufigster_tipp": "-:-",
            "anzahl_4": 0,
            "anzahl_3": 0,
            "anzahl_2": 0
        },
        {
            "spiel": "Marokko vs. Haiti",
            "phase": "Gruppe",
            "beendet": false,
            "ergebnis": "-:-",
            "haeufigster_tipp": "-:-",
            "anzahl_4": 0,
            "anzahl_3": 0,
            "anzahl_2": 0
        },
        {
            "spiel": "Schottland vs. Brasilien",
            "phase": "Gruppe",
            "beendet": false,
            "ergebnis": "-:-",
            "haeufigster_tipp": "-:-",
            "anzahl_4": 0,
            "anzahl_3": 0,
            "anzahl_2": 0
        },
        {
            "spiel": "Südafrika vs. Südkorea",
            "phase": "Gruppe",
            "beendet": false,
            "ergebnis": "-:-",
            "haeufigster_tipp": "-:-",
            "anzahl_4": 0,
            "anzahl_3": 0,
            "anzahl_2": 0
        },
        {
            "spiel": "Tschechien vs. Mexiko",
            "phase": "Gruppe",
            "beendet": false,
            "ergebnis": "-:-",
            "haeufigster_tipp": "-:-",
            "anzahl_4": 0,
            "anzahl_3": 0,
            "anzahl_2": 0
        },
        {
            "spiel": "Ecuador vs. DEUTSCHLAND",
            "phase": "Gruppe",
            "beendet": false,
            "ergebnis": "-:-",
            "haeufigster_tipp": "-:-",
            "anzahl_4": 0,
            "anzahl_3": 0,
            "anzahl_2": 0
        },
        {
            "spiel": "Curacao vs. Elfenbeinküste",
            "phase": "Gruppe",
            "beendet": false,
            "ergebnis": "-:-",
            "haeufigster_tipp": "-:-",
            "anzahl_4": 0,
            "anzahl_3": 0,
            "anzahl_2": 0
        },
        {
            "spiel": "Tunesien vs. Niederlande",
            "phase": "Gruppe",
            "beendet": false,
            "ergebnis": "-:-",
            "haeufigster_tipp": "-:-",
            "anzahl_4": 0,
            "anzahl_3": 0,
            "anzahl_2": 0
        },
        {
            "spiel": "Japan vs. Schweden",
            "phase": "Gruppe",
            "beendet": false,
            "ergebnis": "-:-",
            "haeufigster_tipp": "-:-",
            "anzahl_4": 0,
            "anzahl_3": 0,
            "anzahl_2": 0
        },
        {
            "spiel": "Türkei vs. USA",
            "phase": "Gruppe",
            "beendet": false,
            "ergebnis": "-:-",
            "haeufigster_tipp": "-:-",
            "anzahl_4": 0,
            "anzahl_3": 0,
            "anzahl_2": 0
        },
        {
            "spiel": "Paraguay vs. Australien",
            "phase": "Gruppe",
            "beendet": false,
            "ergebnis": "-:-",
            "haeufigster_tipp": "-:-",
            "anzahl_4": 0,
            "anzahl_3": 0,
            "anzahl_2": 0
        },
        {
            "spiel": "Norwegen vs. Frankreich",
            "phase": "Gruppe",
            "beendet": false,
            "ergebnis": "-:-",
            "haeufigster_tipp": "-:-",
            "anzahl_4": 0,
            "anzahl_3": 0,
            "anzahl_2": 0
        },
        {
            "spiel": "Senegal vs. Irak",
            "phase": "Gruppe",
            "beendet": false,
            "ergebnis": "-:-",
            "haeufigster_tipp": "-:-",
            "anzahl_4": 0,
            "anzahl_3": 0,
            "anzahl_2": 0
        },
        {
            "spiel": "Neuseeland vs. Belgien",
            "phase": "Gruppe",
            "beendet": false,
            "ergebnis": "-:-",
            "haeufigster_tipp": "-:-",
            "anzahl_4": 0,
            "anzahl_3": 0,
            "anzahl_2": 0
        },
        {
            "spiel": "Ägypten vs. Iran",
            "phase": "Gruppe",
            "beendet": false,
            "ergebnis": "-:-",
            "haeufigster_tipp": "-:-",
            "anzahl_4": 0,
            "anzahl_3": 0,
            "anzahl_2": 0
        },
        {
            "spiel": "Uruguay vs. Spanien",
            "phase": "Gruppe",
            "beendet": false,
            "ergebnis": "-:-",
            "haeufigster_tipp": "-:-",
            "anzahl_4": 0,
            "anzahl_3": 0,
            "anzahl_2": 0
        },
        {
            "spiel": "Kap Verde vs. Saudi-Arabien",
            "phase": "Gruppe",
            "beendet": false,
            "ergebnis": "-:-",
            "haeufigster_tipp": "-:-",
            "anzahl_4": 0,
            "anzahl_3": 0,
            "anzahl_2": 0
        },
        {
            "spiel": "Panama vs. England",
            "phase": "Gruppe",
            "beendet": false,
            "ergebnis": "-:-",
            "haeufigster_tipp": "-:-",
            "anzahl_4": 0,
            "anzahl_3": 0,
            "anzahl_2": 0
        },
        {
            "spiel": "Kroatien vs. Ghana",
            "phase": "Gruppe",
            "beendet": false,
            "ergebnis": "-:-",
            "haeufigster_tipp": "-:-",
            "anzahl_4": 0,
            "anzahl_3": 0,
            "anzahl_2": 0
        },
        {
            "spiel": "Jordanien vs. Argentinien",
            "phase": "Gruppe",
            "beendet": false,
            "ergebnis": "-:-",
            "haeufigster_tipp": "-:-",
            "anzahl_4": 0,
            "anzahl_3": 0,
            "anzahl_2": 0
        },
        {
            "spiel": "Algerien vs. Österreich",
            "phase": "Gruppe",
            "beendet": false,
            "ergebnis": "-:-",
            "haeufigster_tipp": "-:-",
            "anzahl_4": 0,
            "anzahl_3": 0,
            "anzahl_2": 0
        },
        {
            "spiel": "Kolumbien vs. Portugal",
            "phase": "Gruppe",
            "beendet": false,
            "ergebnis": "-:-",
            "haeufigster_tipp": "-:-",
            "anzahl_4": 0,
            "anzahl_3": 0,
            "anzahl_2": 0
        },
        {
            "spiel": "DRK vs. Usbekistan",
            "phase": "Gruppe",
            "beendet": false,
            "ergebnis": "-:-",
            "haeufigster_tipp": "-:-",
            "anzahl_4": 0,
            "anzahl_3": 0,
            "anzahl_2": 0
        },
        {
            "spiel": "Südkorea vs. Schweiz",
            "phase": "K.o.",
            "beendet": false,
            "ergebnis": "-:-",
            "haeufigster_tipp": "-:-",
            "anzahl_4": 0,
            "anzahl_3": 0,
            "anzahl_2": 0
        },
        {
            "spiel": "DEUTSCHLAND vs. Schweden",
            "phase": "K.o.",
            "beendet": false,
            "ergebnis": "-:-",
            "haeufigster_tipp": "-:-",
            "anzahl_4": 0,
            "anzahl_3": 0,
            "anzahl_2": 0
        },
        {
            "spiel": "Niederlande vs. Marokko",
            "phase": "K.o.",
            "beendet": false,
            "ergebnis": "-:-",
            "haeufigster_tipp": "-:-",
            "anzahl_4": 0,
            "anzahl_3": 0,
            "anzahl_2": 0
        },
        {
            "spiel": "Brasilien vs. Japan",
            "phase": "K.o.",
            "beendet": false,
            "ergebnis": "-:-",
            "haeufigster_tipp": "-:-",
            "anzahl_4": 0,
            "anzahl_3": 0,
            "anzahl_2": 0
        },
        {
            "spiel": "Frankreich vs. Schottland",
            "phase": "K.o.",
            "beendet": false,
            "ergebnis": "-:-",
            "haeufigster_tipp": "-:-",
            "anzahl_4": 0,
            "anzahl_3": 0,
            "anzahl_2": 0
        },
        {
            "spiel": "Elfenbeinküste vs. Norwegen",
            "phase": "K.o.",
            "beendet": false,
            "ergebnis": "-:-",
            "haeufigster_tipp": "-:-",
            "anzahl_4": 0,
            "anzahl_3": 0,
            "anzahl_2": 0
        },
        {
            "spiel": "Mexiko vs. Kap Verde",
            "phase": "K.o.",
            "beendet": false,
            "ergebnis": "-:-",
            "haeufigster_tipp": "-:-",
            "anzahl_4": 0,
            "anzahl_3": 0,
            "anzahl_2": 0
        },
        {
            "spiel": "England vs. DRK",
            "phase": "K.o.",
            "beendet": false,
            "ergebnis": "-:-",
            "haeufigster_tipp": "-:-",
            "anzahl_4": 0,
            "anzahl_3": 0,
            "anzahl_2": 0
        },
        {
            "spiel": "USA vs. Algerien",
            "phase": "K.o.",
            "beendet": false,
            "ergebnis": "-:-",
            "haeufigster_tipp": "-:-",
            "anzahl_4": 0,
            "anzahl_3": 0,
            "anzahl_2": 0
        },
        {
            "spiel": "Ägypten vs. Tschechien",
            "phase": "K.o.",
            "beendet": false,
            "ergebnis": "-:-",
            "haeufigster_tipp": "-:-",
            "anzahl_4": 0,
            "anzahl_3": 0,
            "anzahl_2": 0
        },
        {
            "spiel": "Portugal vs. Ghana",
            "phase": "K.o.",
            "beendet": false,
            "ergebnis": "-:-",
            "haeufigster_tipp": "-:-",
            "anzahl_4": 0,
            "anzahl_3": 0,
            "anzahl_2": 0
        },
        {
            "spiel": "Spanien vs. Österreich",
            "phase": "K.o.",
            "beendet": false,
            "ergebnis": "-:-",
            "haeufigster_tipp": "-:-",
            "anzahl_4": 0,
            "anzahl_3": 0,
            "anzahl_2": 0
        },
        {
            "spiel": "Kanada vs. Belgien",
            "phase": "K.o.",
            "beendet": false,
            "ergebnis": "-:-",
            "haeufigster_tipp": "-:-",
            "anzahl_4": 0,
            "anzahl_3": 0,
            "anzahl_2": 0
        },
        {
            "spiel": "Argentinien vs. Uruguay",
            "phase": "K.o.",
            "beendet": false,
            "ergebnis": "-:-",
            "haeufigster_tipp": "-:-",
            "anzahl_4": 0,
            "anzahl_3": 0,
            "anzahl_2": 0
        },
        {
            "spiel": "Kolumbien vs. Paraguay",
            "phase": "K.o.",
            "beendet": false,
            "ergebnis": "-:-",
            "haeufigster_tipp": "-:-",
            "anzahl_4": 0,
            "anzahl_3": 0,
            "anzahl_2": 0
        },
        {
            "spiel": "Australien vs. Iran",
            "phase": "K.o.",
            "beendet": false,
            "ergebnis": "-:-",
            "haeufigster_tipp": "-:-",
            "anzahl_4": 0,
            "anzahl_3": 0,
            "anzahl_2": 0
        },
        {
            "spiel": "WARTEND vs. WARTEND",
            "phase": "K.o.",
            "beendet": false,
            "ergebnis": "-:-",
            "haeufigster_tipp": "-:-",
            "anzahl_4": 0,
            "anzahl_3": 0,
            "anzahl_2": 0
        },
        {
            "spiel": "WARTEND vs. WARTEND",
            "phase": "K.o.",
            "beendet": false,
            "ergebnis": "-:-",
            "haeufigster_tipp": "-:-",
            "anzahl_4": 0,
            "anzahl_3": 0,
            "anzahl_2": 0
        },
        {
            "spiel": "WARTEND vs. WARTEND",
            "phase": "K.o.",
            "beendet": false,
            "ergebnis": "-:-",
            "haeufigster_tipp": "-:-",
            "anzahl_4": 0,
            "anzahl_3": 0,
            "anzahl_2": 0
        },
        {
            "spiel": "WARTEND vs. WARTEND",
            "phase": "K.o.",
            "beendet": false,
            "ergebnis": "-:-",
            "haeufigster_tipp": "-:-",
            "anzahl_4": 0,
            "anzahl_3": 0,
            "anzahl_2": 0
        },
        {
            "spiel": "WARTEND vs. WARTEND",
            "phase": "K.o.",
            "beendet": false,
            "ergebnis": "-:-",
            "haeufigster_tipp": "-:-",
            "anzahl_4": 0,
            "anzahl_3": 0,
            "anzahl_2": 0
        },
        {
            "spiel": "WARTEND vs. WARTEND",
            "phase": "K.o.",
            "beendet": false,
            "ergebnis": "-:-",
            "haeufigster_tipp": "-:-",
            "anzahl_4": 0,
            "anzahl_3": 0,
            "anzahl_2": 0
        },
        {
            "spiel": "WARTEND vs. WARTEND",
            "phase": "K.o.",
            "beendet": false,
            "ergebnis": "-:-",
            "haeufigster_tipp": "-:-",
            "anzahl_4": 0,
            "anzahl_3": 0,
            "anzahl_2": 0
        },
        {
            "spiel": "WARTEND vs. WARTEND",
            "phase": "K.o.",
            "beendet": false,
            "ergebnis": "-:-",
            "haeufigster_tipp": "-:-",
            "anzahl_4": 0,
            "anzahl_3": 0,
            "anzahl_2": 0
        },
        {
            "spiel": "WARTEND vs. WARTEND",
            "phase": "K.o.",
            "beendet": false,
            "ergebnis": "-:-",
            "haeufigster_tipp": "-:-",
            "anzahl_4": 0,
            "anzahl_3": 0,
            "anzahl_2": 0
        },
        {
            "spiel": "WARTEND vs. WARTEND",
            "phase": "K.o.",
            "beendet": false,
            "ergebnis": "-:-",
            "haeufigster_tipp": "-:-",
            "anzahl_4": 0,
            "anzahl_3": 0,
            "anzahl_2": 0
        },
        {
            "spiel": "WARTEND vs. WARTEND",
            "phase": "K.o.",
            "beendet": false,
            "ergebnis": "-:-",
            "haeufigster_tipp": "-:-",
            "anzahl_4": 0,
            "anzahl_3": 0,
            "anzahl_2": 0
        },
        {
            "spiel": "WARTEND vs. WARTEND",
            "phase": "K.o.",
            "beendet": false,
            "ergebnis": "-:-",
            "haeufigster_tipp": "-:-",
            "anzahl_4": 0,
            "anzahl_3": 0,
            "anzahl_2": 0
        },
        {
            "spiel": "WARTEND vs. WARTEND",
            "phase": "K.o.",
            "beendet": false,
            "ergebnis": "-:-",
            "haeufigster_tipp": "-:-",
            "anzahl_4": 0,
            "anzahl_3": 0,
            "anzahl_2": 0
        },
        {
            "spiel": "WARTEND vs. WARTEND",
            "phase": "K.o.",
            "beendet": false,
            "ergebnis": "-:-",
            "haeufigster_tipp": "-:-",
            "anzahl_4": 0,
            "anzahl_3": 0,
            "anzahl_2": 0
        },
        {
            "spiel": "WARTEND vs. WARTEND",
            "phase": "K.o.",
            "beendet": false,
            "ergebnis": "-:-",
            "haeufigster_tipp": "-:-",
            "anzahl_4": 0,
            "anzahl_3": 0,
            "anzahl_2": 0
        },
        {
            "spiel": "WARTEND vs. WARTEND",
            "phase": "K.o.",
            "beendet": false,
            "ergebnis": "-:-",
            "haeufigster_tipp": "-:-",
            "anzahl_4": 0,
            "anzahl_3": 0,
            "anzahl_2": 0
        }
    ]
}